jupyterlab_courselevels/__init__.py
jupyterlab_courselevels/_version.py
jupyterlab_courselevels-0.8.1.data/data/share/jupyter/labextensions/jupyterlab-courselevels/build_log.json
jupyterlab_courselevels-0.8.1.data/data/share/jupyter/labextensions/jupyterlab-courselevels/package.json
jupyterlab_courselevels-0.8.1.data/data/share/jupyter/labextensions/jupyterlab-courselevels/schemas/jupyterlab-courselevels/package.json.orig
jupyterlab_courselevels-0.8.1.data/data/share/jupyter/labextensions/jupyterlab-courselevels/schemas/jupyterlab-courselevels/plugin.json
jupyterlab_courselevels-0.8.1.data/data/share/jupyter/labextensions/jupyterlab-courselevels/static/lib_index_js.25fbe2f6581d0a777b1f.js
jupyterlab_courselevels-0.8.1.data/data/share/jupyter/labextensions/jupyterlab-courselevels/static/lib_index_js.25fbe2f6581d0a777b1f.js.map
jupyterlab_courselevels-0.8.1.data/data/share/jupyter/labextensions/jupyterlab-courselevels/static/lib_index_js.3de9501ec3a0c88836bb.js
jupyterlab_courselevels-0.8.1.data/data/share/jupyter/labextensions/jupyterlab-courselevels/static/lib_index_js.3de9501ec3a0c88836bb.js.map
jupyterlab_courselevels-0.8.1.data/data/share/jupyter/labextensions/jupyterlab-courselevels/static/lib_index_js.a5145521343950b351b7.js
jupyterlab_courselevels-0.8.1.data/data/share/jupyter/labextensions/jupyterlab-courselevels/static/lib_index_js.a5145521343950b351b7.js.map
jupyterlab_courselevels-0.8.1.data/data/share/jupyter/labextensions/jupyterlab-courselevels/static/lib_index_js.cf91f028dc5a1c30b067.js
jupyterlab_courselevels-0.8.1.data/data/share/jupyter/labextensions/jupyterlab-courselevels/static/lib_index_js.cf91f028dc5a1c30b067.js.map
jupyterlab_courselevels-0.8.1.data/data/share/jupyter/labextensions/jupyterlab-courselevels/static/remoteEntry.4d4f620bee2c920894b2.js.map
jupyterlab_courselevels-0.8.1.data/data/share/jupyter/labextensions/jupyterlab-courselevels/static/remoteEntry.6579e183dbe72c61ee72.js.map
jupyterlab_courselevels-0.8.1.dist-info/METADATA
jupyterlab_courselevels-0.8.1.dist-info/WHEEL
jupyterlab_courselevels-0.8.1.dist-info/licenses/LICENSE
jupyterlab_courselevels-0.8.1.dist-info/RECORD
