Metadata-Version: 2.3
Name: jupyterlab_courselevels
Version: 0.8.1
Dynamic: Keywords
Summary: Jlab extension for showing course levels and structure
Project-URL: Homepage, https://github.com/parmentelat/jupyterlab-courselevels
Project-URL: Bug Tracker, https://github.com/parmentelat/jupyterlab-courselevels/issues
Project-URL: Repository, https://github.com/parmentelat/jupyterlab-courselevels.git
Author-email: Thierry Parmentelat <thierry.parmentelat@inria.fr>
License: BSD 3-Clause License
License-File: LICENSE
Classifier: Framework :: Jupyter
Classifier: Framework :: Jupyter :: JupyterLab
Classifier: Framework :: Jupyter :: JupyterLab :: 4
Classifier: Framework :: Jupyter :: JupyterLab :: Extensions
Classifier: Framework :: Jupyter :: JupyterLab :: Extensions :: Prebuilt
Classifier: License :: OSI Approved :: BSD License
Classifier: Programming Language :: Python
Classifier: Programming Language :: Python :: 3
Classifier: Programming Language :: Python :: 3.8
Classifier: Programming Language :: Python :: 3.9
Classifier: Programming Language :: Python :: 3.10
Classifier: Programming Language :: Python :: 3.11
Requires-Python: >=3.8
Requires-Dist: jupyterlab-celltagsclasses
Requires-Dist: jupyterlab-hidecell
Requires-Dist: jupyterlab-myst
